setup.py
argparseplus/__init__.py
argparseplus.egg-info/PKG-INFO
argparseplus.egg-info/SOURCES.txt
argparseplus.egg-info/dependency_links.txt
argparseplus.egg-info/top_level.txt