Metadata-Version: 1.0
Name: argparseplus
Version: 2.0.0
Summary: argparse extensions.
Home-page: https://bitbucket.org/jodier/argparseplus
Author: Jerome Odier
Author-email: jerome.odier@cern.ch
License: CeCILL-C
Platform: UNKNOWN
